draversal.py
draversal/DictSearchQuery.py
draversal/DictTraversal.py
draversal/__init__.py
tests/__init__.py
tests/test_draversal.py
tests/test_draversal_current_item.py
tests/test_draversal_inverted.py
tests/test_draversal_new_context.py
tests/test_draversal_search.py
draversal-0.1.5.dist-info/LICENSE
draversal-0.1.5.dist-info/METADATA
draversal-0.1.5.dist-info/WHEEL
draversal-0.1.5.dist-info/top_level.txt
draversal-0.1.5.dist-info/RECORD
